LICENSE
MANIFEST.in
README.rst
setup.py
django_lockout.egg-info/PKG-INFO
django_lockout.egg-info/SOURCES.txt
django_lockout.egg-info/dependency_links.txt
django_lockout.egg-info/requires.txt
django_lockout.egg-info/top_level.txt
lockout/__init__.py
lockout/decorators.py
lockout/exceptions.py
lockout/middleware.py
lockout/models.py
lockout/settings.py
lockout/tests.py
lockout/utils.py