Metadata-Version: 1.0
Name: django-lockout
Version: 0.1.1
Summary: cache-based Django app that locks out users after too many failed login attempts.
Home-page: https://github.com/brianjaystanley/django-lockout
Author: Brian Jay Stanley
Author-email: brian@brianjaystanley.com
License: MIT
Keywords: django cache security
Platform: UNKNOWN
Classifier: Development Status :: 4 - Beta
Classifier: Framework :: Django
Classifier: Intended Audience :: Developers
Classifier: License :: OSI Approved :: MIT License
Classifier: Operating System :: OS Independent
Classifier: Programming Language :: Python
Classifier: Topic :: Internet :: WWW/HTTP :: Dynamic Content
Classifier: Topic :: Security
Classifier: Topic :: Software Development :: Libraries
Classifier: Topic :: Software Development :: Libraries :: Python Modules
